[
    {
        "type": "title",
        "content": "യൽദോ (ഡിസംബർ 25)"
    },
    {
        "type": "subheading",
        "content": "(ഒന്നാം രാഗം)"
    },
    {
        "type": "link",
        "file": "qurbanaSongs/yeldho/eveningGospel.json"
    },
    {
        "type": "link",
        "file": "qurbanaSongs/yeldho/morningGospel.json"
    },
    {
        "type": "link",
        "file": "qurbanaSongs/yeldho/qurbanaGospel.json"
    },
    {
        "type": "link",
        "file": "qurbanaSongs/yeldho/kasolikki.json"
    },
    {
        "type": "link",
        "file": "qurbanaSongs/yeldho/hoothomo.json"
    },
    {
        "type": "link",
        "file": "qurbanaSongs/yeldho/duringCommunion.json"
    }
]